selfdiscord/__init__.py
selfdiscord/errors.py
selfdiscord/route.py
selfdiscord/selfdiscord.py
SelfDiscord-0.6.dist-info/LICENSE
SelfDiscord-0.6.dist-info/METADATA
SelfDiscord-0.6.dist-info/WHEEL
SelfDiscord-0.6.dist-info/top_level.txt
SelfDiscord-0.6.dist-info/RECORD
