Metadata-Version: 2.1
Name: SelfDiscord
Version: 0.6
Summary: Discord API Wrapper for Self Bots
Home-page: https://github.com/RedBallG/SelfDiscord
Author: RedBallG
License: MIT
Project-URL: Documentation, https://github.com/RedBallG/SelfDiscord/tree/main/docs
Project-URL: Issue tracker, https://github.com/RedBallG/SelfDiscord/issues
Platform: UNKNOWN
Classifier: Development Status :: 5 - Production/Stable
Classifier: License :: OSI Approved :: MIT License
Classifier: Intended Audience :: Developers
Classifier: Natural Language :: English
Classifier: Operating System :: OS Independent
Classifier: Programming Language :: Python :: 3.5
Classifier: Programming Language :: Python :: 3.6
Classifier: Programming Language :: Python :: 3.7
Classifier: Programming Language :: Python :: 3.8
Classifier: Programming Language :: Python :: 3.9
Classifier: Topic :: Internet
Classifier: Topic :: Software Development :: Libraries
Classifier: Topic :: Software Development :: Libraries :: Python Modules
Classifier: Topic :: Utilities
Requires-Python: >=3.5.3
Requires-Dist: requests
